glitchtipcli/__init__.py
glitchtipcli/glitchtipcli.py
glitchtip_cli-1.0.1.dist-info/LICENSE
glitchtip_cli-1.0.1.dist-info/METADATA
glitchtip_cli-1.0.1.dist-info/WHEEL
glitchtip_cli-1.0.1.dist-info/entry_points.txt
glitchtip_cli-1.0.1.dist-info/top_level.txt
glitchtip_cli-1.0.1.dist-info/RECORD
