Metadata-Version: 2.1
Name: glitchtip-cli
Version: 1.0.1
Summary: A Glicthtip CLI
Author-email: Mark Freer <mfreer@redhat.com>, Petr Babic <pbabic@redhat.com>
License: Apache License
Project-URL: Homepage, https://gitlab.cee.redhat.com/cssre/glitchtipcli
Classifier: Programming Language :: Python :: 3
Classifier: License :: OSI Approved :: Apache Software License
Classifier: Operating System :: OS Independent
Requires-Python: >=3.8
License-File: LICENSE
Requires-Dist: aiohttp (==3.8.1)
Requires-Dist: aiosignal (==1.2.0)
Requires-Dist: anyio (==3.6.1)
Requires-Dist: async-timeout (==4.0.2)
Requires-Dist: attrs (==21.4.0)
Requires-Dist: autopep8 (==1.6.0)
Requires-Dist: ascii-magic (==1.6)
Requires-Dist: black (==22.6.0)
Requires-Dist: certifi (==2022.6.15)
Requires-Dist: charset-normalizer (==2.0.12)
Requires-Dist: click (==8.1.3)
Requires-Dist: commonmark (==0.9.1)
Requires-Dist: emoji (==1.7.0)
Requires-Dist: frozenlist (==1.3.0)
Requires-Dist: h11 (==0.12.0)
Requires-Dist: httpcore (==0.15.0)
Requires-Dist: httpx (==0.23.0)
Requires-Dist: idna (==3.3)
Requires-Dist: multidict (==6.0.2)
Requires-Dist: mypy-extensions (==0.4.3)
Requires-Dist: pathspec (==0.9.0)
Requires-Dist: platformdirs (==2.5.2)
Requires-Dist: pycodestyle (==2.8.0)
Requires-Dist: pyfiglet (==0.8.post1)
Requires-Dist: Pygments (==2.12.0)
Requires-Dist: python-dotenv (==0.20.0)
Requires-Dist: pytest (==7.1.3)
Requires-Dist: Pillow (==9.0)
Requires-Dist: requests (==2.28.0)
Requires-Dist: responses (==0.22.0)
Requires-Dist: rfc3986 (==1.5.0)
Requires-Dist: rich (==12.4.4)
Requires-Dist: sniffio (==1.2.0)
Requires-Dist: tabulate (==0.8.10)
Requires-Dist: toml (==0.10.2)
Requires-Dist: tomli (==2.0.1)
Requires-Dist: typing-extensions (==4.2.0)
Requires-Dist: urllib3 (==1.26.9)
Requires-Dist: watchdog (==2.1.9)
Requires-Dist: yarl (==1.7.2)
Requires-Dist: yaspin (==2.2.0)
